bundestag_api/__init__.py
bundestag_api/__main__.py
bundestag_api/bta_wrapper.py
bundestag_api/models.py
bundestag_api/utils.py
bundestag_api-1.3.0.dist-info/licenses/LICENSE
bundestag_api-1.3.0.dist-info/METADATA
bundestag_api-1.3.0.dist-info/WHEEL
bundestag_api-1.3.0.dist-info/top_level.txt
bundestag_api-1.3.0.dist-info/RECORD
