Metadata-Version: 2.4
Name: bundestag_api
Version: 1.3.0
Summary: Python wrapper for the official Bundestag-API
Home-page: https://github.com/jschibberges/Bundestag-API
Author: Julian Schibberges
Author-email: Julian Schibberges <julian@schibberges.de>
License: MIT
Project-URL: Homepage, https://github.com/jschibberges/Bundestag-API
Project-URL: Repository, https://github.com/jschibberges/Bundestag-API
Project-URL: Issues, https://github.com/jschibberges/Bundestag-API/issues
Keywords: bundestag,api,parliament,germany,german,politics,political,data,legislation,legislative,federal,documents,drucksache,plenarprotokoll,politicians,government,democracy,deutscher-bundestag,parliamentary,open-data,civic-tech,transparency,political-science,policy,bundesrepublik,deutschland
Classifier: Development Status :: 4 - Beta
Classifier: Intended Audience :: Developers
Classifier: Intended Audience :: Science/Research
Classifier: Intended Audience :: Education
Classifier: Intended Audience :: Legal Industry
Classifier: Intended Audience :: Information Technology
Classifier: License :: OSI Approved :: MIT License
Classifier: Natural Language :: English
Classifier: Natural Language :: German
Classifier: Operating System :: OS Independent
Classifier: Programming Language :: Python :: 3
Classifier: Programming Language :: Python :: 3.7
Classifier: Programming Language :: Python :: 3.8
Classifier: Programming Language :: Python :: 3.9
Classifier: Programming Language :: Python :: 3.10
Classifier: Programming Language :: Python :: 3.11
Classifier: Programming Language :: Python :: 3.12
Classifier: Programming Language :: Python :: 3 :: Only
Classifier: Topic :: Internet :: WWW/HTTP :: Dynamic Content
Classifier: Topic :: Scientific/Engineering :: Information Analysis
Classifier: Topic :: Sociology :: History
Classifier: Topic :: Software Development :: Libraries :: Python Modules
Classifier: Topic :: Text Processing :: General
Classifier: Topic :: Database :: Front-Ends
Requires-Python: >=3.7.0
License-File: LICENSE
Requires-Dist: requests>=2.0.0
Provides-Extra: pandas
Requires-Dist: pandas>=1.2.0; extra == "pandas"
Provides-Extra: dev
Requires-Dist: pytest; extra == "dev"
Requires-Dist: openpyxl>3.0.0; extra == "dev"
Requires-Dist: pandas>1.2.0; extra == "dev"
Dynamic: author
Dynamic: home-page
Dynamic: license-file
Dynamic: requires-python
